{
	"animations": [
		{
			"offsets": [0, 1],
			"loop": false,
			"fps": 24,
			"anim": "idle",
			"indices": [],
			"name": "bf_mayo idle"
		},
		{
			"offsets": [1, 1],
			"loop": false,
			"fps": 24,
			"anim": "singLEFT",
			"indices": [],
			"name": "bf_mayo left"
		},
		{
			"offsets": [-2, -50],
			"loop": false,
			"fps": 24,
			"anim": "singDOWN",
			"indices": [],
			"name": "bf_mayo down"
		},
		{
			"offsets": [0, 2],
			"loop": false,
			"fps": 24,
			"anim": "singUP",
			"indices": [],
			"name": "bf_mayo up"
		},
		{
			"offsets": [-38, -4],
			"loop": false,
			"fps": 24,
			"anim": "singRIGHT",
			"indices": [],
			"name": "bf_mayo right"
		}
	],
	"vocals_file": "",
	"no_antialiasing": false,
	"image": "characters/bf_mayo",
	"position": [-270, -130],
	"healthicon": "bf",
	"flip_x": true,
	"healthbar_colors": [49, 176, 209],
	"camera_position": [0, 20],
	"sing_duration": 4,
	"scale": 0.9,
	"_editor_isPlayer": true
}